newsletter_subscription/__init__.py
newsletter_subscription/ajax_views.py
newsletter_subscription/backend.py
newsletter_subscription/models.py
newsletter_subscription/urls.py
newsletter_subscription/utils.py
newsletter_subscription/views.py
newsletter_subscription/locale/de/LC_MESSAGES/django.mo
newsletter_subscription/locale/de/LC_MESSAGES/django.po
newsletter_subscription/templates/newsletter_subscription/form.html
newsletter_subscription/templates/newsletter_subscription/subscribe.html
newsletter_subscription/templates/newsletter_subscription/subscription_email.txt
newsletter_subscription/templates/newsletter_subscription/unsubscription_email.txt
django_newsletter_subscription-0.5.0.dist-info/LICENSE
django_newsletter_subscription-0.5.0.dist-info/METADATA
django_newsletter_subscription-0.5.0.dist-info/WHEEL
django_newsletter_subscription-0.5.0.dist-info/top_level.txt
django_newsletter_subscription-0.5.0.dist-info/RECORD
